<?xml version="1.0" encoding="UTF-8"?><record_update>
    <sys_choice action="INSERT_OR_UPDATE" field="build_completed" table="var__m_sys_hub_flow_output_b5de439a1b8ecc5033fbdbd3cc4bcbee" version="3">
        <sys_choice action="INSERT_OR_UPDATE">
            <dependent_value/>
            <element>build_completed</element>
            <hint/>
            <inactive>false</inactive>
            <label>True</label>
            <language>en</language>
            <name>var__m_sys_hub_flow_output_b5de439a1b8ecc5033fbdbd3cc4bcbee</name>
            <sequence>1</sequence>
            <sys_created_by>admin</sys_created_by>
            <sys_created_on>2020-01-02 11:54:05</sys_created_on>
            <sys_domain>global</sys_domain>
            <sys_domain_path>/</sys_domain_path>
            <sys_id>0ade839a1b8ecc5033fbdbd3cc4bcb41</sys_id>
            <sys_mod_count>0</sys_mod_count>
            <sys_updated_by>admin</sys_updated_by>
            <sys_updated_on>2020-01-02 11:54:05</sys_updated_on>
            <value>True</value>
        </sys_choice>
        <sys_choice action="INSERT_OR_UPDATE">
            <dependent_value/>
            <element>build_completed</element>
            <hint/>
            <inactive>false</inactive>
            <label>False</label>
            <language>en</language>
            <name>var__m_sys_hub_flow_output_b5de439a1b8ecc5033fbdbd3cc4bcbee</name>
            <sequence>2</sequence>
            <sys_created_by>admin</sys_created_by>
            <sys_created_on>2020-01-02 11:54:05</sys_created_on>
            <sys_domain>global</sys_domain>
            <sys_domain_path>/</sys_domain_path>
            <sys_id>cade839a1b8ecc5033fbdbd3cc4bcb42</sys_id>
            <sys_mod_count>0</sys_mod_count>
            <sys_updated_by>admin</sys_updated_by>
            <sys_updated_on>2020-01-02 11:54:05</sys_updated_on>
            <value>False</value>
        </sys_choice>
        <sys_choice_set action="INSERT_OR_UPDATE">
            <element>build_completed</element>
            <name>var__m_sys_hub_flow_output_b5de439a1b8ecc5033fbdbd3cc4bcbee</name>
            <sys_class_name>sys_choice_set</sys_class_name>
            <sys_created_by>admin</sys_created_by>
            <sys_created_on>2020-01-02 11:54:05</sys_created_on>
            <sys_id>42de839a1b8ecc5033fbdbd3cc4bcb42</sys_id>
            <sys_mod_count>0</sys_mod_count>
            <sys_name/>
            <sys_package display_value="Jenkins v2" source="x_snc_jenkins_v2">c66af1ca1b8a8c5033fbdbd3cc4bcb75</sys_package>
            <sys_policy/>
            <sys_scope display_value="Jenkins v2">c66af1ca1b8a8c5033fbdbd3cc4bcb75</sys_scope>
            <sys_update_name/>
            <sys_updated_by>admin</sys_updated_by>
            <sys_updated_on>2020-01-02 11:54:05</sys_updated_on>
        </sys_choice_set>
    </sys_choice>
</record_update>
